eaglewrap/__init__.py
eaglewrap/__main__.py
eaglewrap/api.py
eaglewrap/bridge.py
eaglewrap/cfg.py
eaglewrap/model.py
eaglewrap/utils.py
eagle_wrap-0.9.0.dist-info/METADATA
eagle_wrap-0.9.0.dist-info/WHEEL
eagle_wrap-0.9.0.dist-info/entry_points.txt
eagle_wrap-0.9.0.dist-info/licenses/LICENSE
eagle_wrap-0.9.0.dist-info/RECORD
