Metadata-Version: 2.4
Name: eagle-wrap
Version: 0.9.0
Summary: Python wrapper for Eagle
Author-email: ZackaryW <36378555+ZackaryW@users.noreply.github.com>
License-File: LICENSE
Requires-Python: >=3.8
Requires-Dist: click>=8.1.7
Requires-Dist: requests>=2.32.3
